didi_notebook_extension/__init__.py
didi_notebook_extension/_version.py
didi_notebook_extension-0.2.7.data/data/share/jupyter/labextensions/didi-notebook-extension/package.json
didi_notebook_extension-0.2.7.data/data/share/jupyter/labextensions/didi-notebook-extension/static/728.adf73d00115832453a58.js
didi_notebook_extension-0.2.7.data/data/share/jupyter/labextensions/didi-notebook-extension/static/958.eb0e437e53b6a86814b4.js
didi_notebook_extension-0.2.7.data/data/share/jupyter/labextensions/didi-notebook-extension/static/remoteEntry.669ff8394f95a035c486.js
didi_notebook_extension-0.2.7.data/data/share/jupyter/labextensions/didi-notebook-extension/static/style.js
didi_notebook_extension-0.2.7.data/data/share/jupyter/labextensions/didi-notebook-extension/static/third-party-licenses.json
didi_notebook_extension-0.2.7.data/data/share/jupyter/labextensions/didi-notebook-extension/install.json
didi_notebook_extension-0.2.7.dist-info/METADATA
didi_notebook_extension-0.2.7.dist-info/WHEEL
didi_notebook_extension-0.2.7.dist-info/licenses/LICENSE
didi_notebook_extension-0.2.7.dist-info/RECORD
