Metadata-Version: 2.3
Name: didi_notebook_extension
Version: 0.2.7
Dynamic: Keywords
Summary: A JupyterLab extension.
Project-URL: Homepage, https://github.com/yobi-maggie/didi-notebook-extension
Project-URL: Bug Tracker, https://github.com/yobi-maggie/didi-notebook-extension/issues
Project-URL: Repository, https://github.com/yobi-maggie/didi-notebook-extension.git
Author-email: dongmeiqi <dongmeiqi@didiglobal.com>
License: BSD 3-Clause License
License-File: LICENSE
Classifier: Framework :: Jupyter
Classifier: Framework :: Jupyter :: JupyterLab
Classifier: Framework :: Jupyter :: JupyterLab :: 4
Classifier: Framework :: Jupyter :: JupyterLab :: Extensions
Classifier: Framework :: Jupyter :: JupyterLab :: Extensions :: Prebuilt
Classifier: License :: OSI Approved :: BSD License
Classifier: Programming Language :: Python
Classifier: Programming Language :: Python :: 3
Classifier: Programming Language :: Python :: 3.8
Classifier: Programming Language :: Python :: 3.9
Classifier: Programming Language :: Python :: 3.10
Classifier: Programming Language :: Python :: 3.11
Classifier: Programming Language :: Python :: 3.12
Requires-Python: >=3.6
